{"eb":[{"w":"eb","t":"abbr. 电子束（Electron Beam）","p":"eb","d":"n a unit of information equal to 1000 petabits or 10^18 bits\nn a unit of information equal to 1000 petabytes or 10^18 bytes\nn a unit of information equal to 1024 pebibytes or 2^60 bytes","x":"i:ebbing/s:ebs","f":29297}],"eba":[{"w":"eba","t":"abbr. 初级工商管理（Elementary Business Arrangement）；紧急制动辅助系统（emergency brake assist system）"}],"eban":[{"w":"eban","t":"[地名] [尼日利亚] 埃班"}],"ebasco":[{"w":"ebasco","t":"abbr. Electric Bond and Share Co. <美国>电力联盟和股份公司"}],"ebaugh":[{"w":"ebaugh","t":"[人名] 伊博"}],"ebay":[{"w":"ebay","t":"电子港湾；易趣（知名网上购物网站）"}],"ebb":[{"w":"ebb","t":"n. 退潮, 衰退\nvi. 潮退, 衰退","p":"eb","d":"n. a gradual decline (in size or strength or power or number)\nn. the outward flow of the tide\nv. flow back or recede","x":"p:ebbed/d:ebbed/s:ebbs/3:ebbs/i:ebbing","g":"ky toefl gre","f":13680}],"ebb and flow":[{"w":"ebb and flow","t":"潮起潮落,起伏,涨落,盛衰"}],"ebb away":[{"w":"ebb away","t":"消逝, 渐渐衰退","p":"eb əˈwei"}],"ebb down":[{"w":"ebb down","t":"[网络] 下降"}],"ebb off":[{"w":"ebb off","t":"[网络] 退潮"}],"ebb out":[{"w":"ebb out","t":"[网络] 退出"}],"ebb tide":[{"w":"ebb tide","t":"退潮","d":"The reflux of tide water; the retiring tide; -- opposed to\n   flood tide."}],"ebb-tide":[{"w":"ebb-tide","t":"n. 退潮, 落潮"}],"ebbecke's reaction":[{"w":"Ebbecke's reaction","t":"[医] 皮划痕反应, 划皮现象"}],"ebbed":[{"w":"ebbed","t":"v. （指潮水）退( ebb的过去式和过去分词 ); 落; 减少; 衰落","p":"ebd","d":"imp. & p. p. of Ebb","x":"0:ebb/1:pd"}],"ebbesen":[{"w":"ebbesen","t":"[人名] 埃布森"}],"ebbet":[{"w":"ebbet","t":"n. [动]绿北螈( 产于美国东部的一种普通绿色蝾螈)","p":"'ebәt"}],"ebbets":[{"w":"ebbets","t":"[人名] 埃贝茨"}],"ebbetts":[{"w":"ebbetts","t":"[人名] 埃贝茨"}],"ebbing":[{"w":"ebbing","t":"v. （指潮水）退( ebb的现在分词 ); 落; 减少; 衰落","p":"ebɪŋ","d":"n a gradual decline (in size or strength or power or number)\nv flow back or recede\nv hem in fish with stakes and nets so as to prevent them from going back into the sea with the ebb\nv fall away or decline","x":"0:eb/1:i/s:ebbings/i:ebbing","f":39444}],"ebbinghans' butter":[{"w":"Ebbinghans' butter","t":"[医] 埃宾豪斯氏测验(检智力)"}],"ebbinghaus test":[{"w":"Ebbinghaus test","t":"[医] 埃宾豪斯氏试验(检智力)"}],"ebbings":[{"w":"ebbings","t":"(ebbing 的复数) v. （指潮水）退( ebb的现在分词 ); 落; 减少; 衰落","d":"plural of ebbing\nn a gradual decline (in size or strength or power or number)\nv flow back or recede\nv hem in fish with stakes and nets so as to prevent them from going back into the sea with the ebb\nv fall away or decline","x":"0:ebbing/1:s"}],"ebbs":[{"w":"ebbs","t":"n. 退潮( ebb的名词复数 ); 落潮; 衰退\nv. （指潮水）退( ebb的第三人称单数 ); 落; 减少; 衰落","p":"ebz","d":"n a gradual decline (in size or strength or power or number)\nn the outward flow of the tide\nv flow back or recede\nv hem in fish with stakes and nets so as to prevent them from going back into the sea with the ebb\nv fall away or decline","x":"0:ebb/1:s3"}],"ebbtide":[{"w":"ebbtide","t":"n. 落潮"}],"ebby":[{"w":"ebby","t":"[人名] 埃比"}],"ebc":[{"w":"EBC","t":"abbr. 教育广播公司（Educational Broadcasting Corporation）；发动机制动控制"}],"ebcdic":[{"w":"EBCDIC","t":"[计] 扩充的二进制编码的十进制交换码","p":"'epsidik"}],"ebcentric circle":[{"w":"ebcentric circle","t":"[电] 离心圆, 偏心圆"}],"ebd":[{"w":"ebd","t":"abbr. 电子制动力分配系统（Electronic Brake force Distribution）；电子束蒸涂"}],"ebdoenzyme":[{"w":"ebdoenzyme","t":"[机] 胞"}],"ebe":[{"w":"ebe","t":"电子束曝光"}],"ebel":[{"w":"ebel","t":"[人名] 埃贝尔"}],"ebeling":[{"w":"ebeling","t":"[人名] 埃贝林"}],"ebelmenite":[{"w":"ebelmenite","t":"钾硬锰矿","p":"'ebәlmә,nait"}],"eben":[{"w":"eben","t":"n. 埃本（等于Ebenezer, 男子名）","p":"'ebәn"}],"ebenaceae":[{"w":"Ebenaceae","t":"n. [植] 柿树科；柿科","p":",ebə'næsii:"}],"ebenales":[{"w":"Ebenales","t":"n. 柿树目","p":"i'benəlis"}],"ebeneous":[{"w":"ebeneous","t":"漆黑的","p":"'ebә,niәs"}],"ebenezer":[{"w":"Ebenezer","t":"埃比尼泽(姓氏)","p":",ebi'ni:zә","f":36376}],"ebenine":[{"w":"ebenine","t":"乌木色","p":"'ebәni:n"}],"ebensburg":[{"w":"ebensburg","t":"[地名] [美国] 埃本斯堡"}],"eber":[{"w":"eber","t":"abbr. EBV-encoded RNA 非洲淋巴细胞瘤病毒编码核糖核酸; equivalent bit error rate 等效误码率; excessive bit error rate 过高误码率"}],"eber's solution":[{"w":"eber's solution","t":"[机] 埃贝尔溶液"}],"eberbach":[{"w":"eberbach","t":"[地名] [德国] 埃伯巴赫"}],"eberhard":[{"w":"Eberhard","t":"埃伯哈德（人名、品牌名）","f":40542}],"eberhardt":[{"w":"eberhardt","t":"[人名] 埃伯哈特"}],"eberhart":[{"w":"eberhart","t":"[人名] 埃伯哈特"}],"eberharter":[{"w":"eberharter","t":"[人名] 埃伯哈特"}],"eberle":[{"w":"eberle","t":"[人名] 埃伯利"}],"eberlein":[{"w":"eberlein","t":"[人名] 埃伯莱因"}],"eberling":[{"w":"eberling","t":"[人名] 埃贝林"}],"eberly":[{"w":"eberly","t":"[人名] 埃伯利"}],"ebers' papyrus":[{"w":"Ebers' papyrus","t":"[医] 埃伯斯氏古医籍"}],"ebers-moll model":[{"w":"Ebers-Moll model","t":"[电] 衣伯-莫尔模型"}],"ebersole":[{"w":"ebersole","t":"[人名] 埃伯索尔"}],"eberson's butter":[{"w":"Eberson's butter","t":"[医] 埃伯森氏试验(检孕)"}],"eberstadt":[{"w":"eberstadt","t":"[人名] 埃伯施塔特; [地名] [德国] 埃伯施塔特"}],"ebert":[{"w":"Ebert","t":"埃伯特（人名）","f":31162}],"eberth's bacillus":[{"w":"Eberth's bacillus","t":"[医] 伤寒杆菌"}],"eberth's lines":[{"w":"Eberth's lines","t":"[医] 埃伯特氏线(心肌)"}],"eberth's perithelium":[{"w":"Eberth's perithelium","t":"[医] 埃伯特氏周皮, 毛细管外周皮"}],"eberthella":[{"w":"Eberthella","t":"[医] 埃[伯特]氏菌属(现属沙门氏菌属)"}],"eberthella belfastiensis":[{"w":"Eberthella belfastiensis","t":"[医] 贝耳法斯特埃氏杆菌"}],"eberthella bentotensis":[{"w":"Eberthella bentotensis","t":"[医] 本托顿氏埃氏杆菌"}],"eberthella dysenteriae":[{"w":"Eberthella dysenteriae","t":"[医] 痢疾埃氏杆菌"}],"eberthella enterica":[{"w":"Eberthella enterica","t":"[医] 肠道埃氏杆菌"}],"eberthella paradysenteriae":[{"w":"Eberthella paradysenteriae","t":"[医] 副痢疾埃氏杆菌"}],"eberthella pyogenes":[{"w":"Eberthella pyogenes","t":"[医] 酿脓性埃氏杆菌"}],"eberthella sp.":[{"w":"Eberthella sp.","t":"[医] 非典型甲型副伤寒杆菌(仙台型)"}],"eberthella talavensis":[{"w":"Eberthella talavensis","t":"[医] 塔拉文氏埃氏杆菌"}],"eberthella typhi":[{"w":"Eberthella typhi","t":"[医] 伤寒埃氏杆菌, 伤寒沙门氏菌"}],"eberthemia":[{"w":"eberthemia","t":"(=eberthaemia)伤寒菌血症","p":",ebә'θi:miә"}],"eberthian":[{"w":"eberthian","t":"[医] 伤寒菌的"}],"eberthian strumitis":[{"w":"eberthian strumitis","t":"[医] 伤寒性甲状腺肿炎"}],"eberthus":[{"w":"Eberthus","t":"[医] 埃[伯特]氏菌属"}],"eberthus typhosus":[{"w":"Eberthus typhosus","t":"[医] 伤寒埃氏杆菌, 伤寒沙门氏菌"}],"ebg":[{"w":"EBG","t":"基于解释的抽象"}],"ebh":[{"w":"ebh","t":"[医][=essential benign hypertension]原发性良性高血压"}],"ebi":[{"w":"ebi","t":"[医][=emetine and bismuth iodide]碘化吐根碱","p":"'ebaɪ"}],"ebicon":[{"w":"ebicon","t":"电子轰击导电性","p":"'ebәkәn"}],"ebiconductivity":[{"w":"ebiconductivity","t":"[电] 因电子打击结果所得到的电导"}],"ebigite":[{"w":"ebigite","t":"铀钙石","p":"'ebi,^ait"}],"ebimar":[{"w":"Ebimar","t":"[化] 埃必马尔(一种硫酸化多糖,取自Chondrus crispus)"}],"ebinger":[{"w":"ebinger","t":"[人名] 埃宾杰"}],"ebionite":[{"w":"Ebionite","t":"[网络] 伊比奥尼派；以便尼；以便尼人","x":"s:ebionites"}],"ebird":[{"w":"ebird","t":"abbr. electron beam ionization semiconductor device 电子束电离半导体器件"}],"ebit":[{"w":"ebit","t":"abbr. earnings before interest and tax 利税前收益率，付息和缴税前盈余; electron-beam ion trap 电子束离子汽水闸"}],"ebitda":[{"w":"ebitda","t":"abbr. earings before interest;  tax; earnings before interest;  taxes"}],"ebk":[{"w":"ebk","t":"abbr. embryonic bovine kidney 胚胎培育的牛肾"}],"ebl":[{"w":"EBL","t":"解释学习"}],"eblaite":[{"w":"Eblaite","t":"n. 埃卜拉语(一种古代闪米特语, 用楔形文字书写在泥板上)","p":"'eblә,ait,'i:b-"}],"eblan":[{"w":"Eblan","t":"n. 埃卜拉语(一种古代闪米特语, 用楔形文字书写在泥板上)","p":"'eblәn,'i:b-"}],"eble":[{"w":"eble","t":"[人名] 埃布尔","x":"3:ebles/s:ebles"}],"ebles":[{"w":"ebles","t":"(eble 的第三人称 -s形式)  [人名] 埃布尔","d":"-s form of eble","x":"0:eble/1:3s"}],"ebling":[{"w":"ebling","t":"[人名] 埃布林"}],"eblis":[{"w":"Eblis","t":"n. (伊斯兰神话中的)恶魔,魔鬼,魔王","p":"'eblis","d":"n (Islam) the principal evil jinni in Islamic mythology"}],"eblnd":[{"w":"Eblnd","t":"[医] E结合(结合能)"}],"ebm":[{"w":"ebm","t":"abbr. electronic bearing marker 电子轴承制造商; expressed breast milk 挤出的母乳"}],"ebmud":[{"w":"ebmud","t":"abbr. East Bay Municipal Utility District 东海湾地方自制区"}],"ebn":[{"w":"EbN","t":"abbr. 东偏北（East By North）；扩张业务网络（Enhanced Business Network）"}],"ebner's fibrils":[{"w":"Ebner's fibrils","t":"[医] 埃伯内氏原纤维, 牙基质原纤维"}],"ebner's glands":[{"w":"Ebner's glands","t":"[医] 埃伯内氏腺(舌腺)"}],"ebner's liquid":[{"w":"Ebner's liquid","t":"[医] 埃伯内氏液(显微镜脱钙溶液)"}],"ebner's reticulum":[{"w":"Ebner's reticulum","t":"[医] 埃勃内氏网, 细精管细胞网"}],"ebo":[{"w":"ebo","t":"[医][=Ebola virus]依波拉病毒"}],"eboat":[{"w":"Eboat","t":"n. <英>(非装甲的)鱼雷快艇","p":"'i:bәjt"}],"ebola":[{"w":"ebola","t":"n. 埃博拉病毒","p":"i'bəulə","d":"n a severe and often fatal disease in humans and nonhuman primates (monkeys and chimpanzees) caused by the Ebola virus; characterized by high fever and severe internal bleeding; can be spread from person to person; is largely limited to Africa"}],"ebola fever":[{"w":"Ebola fever","t":"n. 埃博拉热病（致命出血热，由病毒引起）","p":"i:'bəʊlə fi:və(r)"}],"ebola hemorrhagic fever":[{"w":"Ebola hemorrhagic fever","t":"[网络] 伊波拉出血热；埃博拉出血热；伊波拉病毒出血热"}],"ebola virus":[{"w":"Ebola virus","t":"伊波拉病毒, 埃博拉病毒（一种肇致出血性发热症线状病毒）","p":"i'bəulə"}],"ebon":[{"w":"ebon","t":"a. 似乌木的","p":"'ebәn","d":"s. of a very dark black","f":39495}],"ebonation":[{"w":"ebonation","t":"[医] 碎骨片清除术"}],"ebone":[{"w":"EBONE","t":"[计] 欧州主干网络"}],"ebonics":[{"w":"Ebonics","t":"n. 黑人英语","p":"'ebəniks","d":"n. a nonstandard form of American English characteristically spoken by African Americans in the United States"}],"ebonies":[{"w":"ebonies","t":"a. 乌木制的, 黑檀木制的；似木的, 黑檀木色的\nn. 乌木, 黑檀\nn. (Ebony)人名；(英)埃博妮","p":"'eb(ə)nɪ","d":"pl.  of Ebony","x":"0:ebony/1:s"}],"ebonise":[{"w":"ebonise","t":"vt.<主英>=ebonize","p":"'ebәnais","d":"v stain black to make it look like ebony"}],"ebonite":[{"w":"ebonite","t":"n. 硬橡胶\n[化] 硬质胶; 硬质橡胶","p":"'ebәnait","d":"n a hard nonresilient rubber formed by vulcanizing natural rubber"}],"ebonite accumulator box":[{"w":"ebonite accumulator box","t":"[化] 硬质胶蓄电箱"}],"ebonite compound":[{"w":"ebonite compound","t":"[化] 硬质胶胶料"}],"ebonite dust":[{"w":"ebonite dust","t":"[化] 硬质胶粉"}],"ebonite for electric industry":[{"w":"ebonite for electric industry","t":"[化] 电气工业用硬质胶"}],"ebonite wax":[{"w":"ebonite wax","t":"[化] 乌木蜡"}],"ebonize":[{"w":"ebonize","t":"vt. 使成乌木色, 使象乌木","p":"'ebәnaiz","d":"v. stain black to make it look like ebony","x":"i:ebonizing/p:ebonized/3:ebonizes/d:ebonized"}],"ebonized":[{"w":"ebonized","t":"v. 使成乌木色, 使像乌木( ebonize的过去式和过去分词 )","d":"v stain black to make it look like ebony","x":"1:pd/0:ebonize","f":40301}],"ebonizes":[{"w":"ebonizes","t":"v. 使成乌木色, 使像乌木( ebonize的第三人称单数 )","d":"v stain black to make it look like ebony","x":"1:3/0:ebonize"}],"ebonizing":[{"w":"ebonizing","t":"v. 使成乌木色, 使像乌木( ebonize的现在分词 )","d":"p. pr. & vb. n. of Ebonize","x":"1:i/0:ebonize"}],"ebony":[{"w":"ebony","t":"n. 乌木\na. 乌木制的","p":"'ebәni","d":"n. hard dark-colored heartwood of the ebony tree; used in cabinetwork and for piano keys\nn. tropical tree of southern Asia having hard dark-colored heartwood used in cabinetwork","x":"s:ebonies","f":15149}],"ebony family":[{"w":"ebony family","t":"[网络] 黑檀树种"}],"ebony spleenwort":[{"w":"ebony spleenwort","t":"[植物]黑柄铁角蕨 (Asplenium platyneuron, 产于北美洲)","p":"ˈebəni: ˈspli:nwə:t"}],"ebony tree":[{"w":"ebony tree","t":"[网络] 乌木树"}],"ebook":[{"w":"ebook","t":"n. 电子书"}],"eboracum":[{"w":"Eboracum","t":"埃勃雷肯[英格兰 York (约克郡)的古代拉丁名(不列颠的罗马省主要城市)]","p":"i'bɔ:rəkəm"}],"eboulement":[{"w":"eboulement","t":"崩坍"}],"ebp":[{"w":"EBP","t":"[化] 稻瘟净"}],"ebracteate":[{"w":"ebracteate","t":"a. (植物)无苞的","p":"i'brækti,eit,-tiit","d":"a without bracts"}],"ebracteolate":[{"w":"ebracteolate","t":"a. 【植物学】 无小苞片的","p":"i'bræktjə,leit","d":"a. Without bracteoles, or little bracts; -- said of a\n   pedicel or flower stalk."}],"ebranlement":[{"w":"ebranlement","t":"[医] 扭除(息肉)"}],"ebrd":[{"w":"EBRD","t":"欧洲复兴开发银行","f":31303}],"ebri":[{"w":"ebri","t":"abbr. Employee Benefit Research Institute 雇员利益调查研究所"}],"ebriecation":[{"w":"ebriecation","t":"[医] 酒狂"}],"ebrietas":[{"w":"ebrietas","t":"[医] 沉醉, 醉酒, 酒精中毒"}],"ebrieties":[{"w":"ebrieties","t":"n. 醉酒","p":"ɪ'braɪətɪ","d":"pl.  of Ebriety"}],"ebriety":[{"w":"ebriety","t":"n. 酩酊\n[医] 沉醉, 醉酒","p":"i'braiәti","d":"n. Drunkenness; intoxication by spirituous liquors;\n   inebriety."}],"ebright":[{"w":"ebright","t":"[人名] 埃布赖特"}],"ebriida":[{"w":"Ebriida","t":"艾鞭目"}],"ebriosity":[{"w":"ebriosity","t":"嗜酒中毒","p":",i:bri'ɔsiti","d":"n. Addiction to drink; habitual drunkenness."}],"ebrlichin":[{"w":"ebrlichin","t":"[医] 艾霉素"}],"ebro":[{"w":"Ebro","t":"n. 埃布罗河(位于西班牙北部)","p":"'eibrәj","d":"n a river in northeastern Spain; flows into the Mediterranean"}],"ebro river":[{"w":"Ebro River","t":"[网络] 埃布罗河；波罗河；埃布罗河畔"}],"ebs":[{"w":"ebs","t":"(eb 的复数) abbr. 电子束（Electron Beam）","d":"plural of eb\nn a unit of information equal to 1000 petabits or 10^18 bits\nn a unit of information equal to 1000 petabytes or 10^18 bytes\nn a unit of information equal to 1024 pebibytes or 2^60 bytes","x":"0:eb/1:s"}],"ebstein's angle":[{"w":"Ebstein's angle","t":"[医] 埃布斯坦氏角, 心肝角"}],"ebstein's diet":[{"w":"Ebstein's diet","t":"[医] 埃布斯坦氏肥胖病饮食"}],"ebstein's disease":[{"w":"Ebstein's disease","t":"[医] 埃布斯坦氏病"}],"ebstein's lesion":[{"w":"Ebstein's lesion","t":"[医] 埃布斯坦氏损害(糖尿病时肾小管上皮细胞透明变性和灶性坏死)"}],"ebstein's leukemia":[{"w":"Ebstein's leukemia","t":"[医] 埃布斯坦氏白血病(超急性白血病)"}],"ebstein's sign":[{"w":"Ebstein's sign","t":"[医] 埃布斯坦氏征(心包大量渗出液时,心肝角呈钝角)"}],"ebstein's treatment":[{"w":"Ebstein's treatment","t":"[医] 埃布斯坦氏疗法(治肥胖病)"}],"ebsworth":[{"w":"ebsworth","t":"[人名] 埃布斯沃思"}],"ebt":[{"w":"ebt","t":"abbr. electron-beam technique 电子束技术; electronic benefits transfer 电子利息转化; earth-based tug (NASA) 地面基站拖拽（美国国家航空和航天局）; examination before trial 测试前的检查"}],"ebuilliometer":[{"w":"ebuilliometer","t":"沸点测定计"}],"ebuillometer":[{"w":"ebuillometer","t":"[机] 沸点测定计"}],"ebullated bed":[{"w":"ebullated bed","t":"[化] 沸腾床; 流化床"}],"ebullationg-bet reactor":[{"w":"ebullationg-bet reactor","t":"[机] 沸腾床反应器"}],"ebullator":[{"w":"ebullator","t":"沸腾器, 循环泵","p":"i'bʌlәtә"}],"ebullience":[{"w":"ebullience","t":"n. 沸腾, 热情, 热情洋溢\n[医] 沸腾","p":"i'bʌljәns","d":"n overflowing with eager enjoyment or approval","g":"gre","f":32546}],"ebulliency":[{"w":"ebulliency","t":"n. 沸腾, （思想、感情等）迸发","p":"ɪ'bʌljənsɪ","d":"n. A boiling up or over; effervescence."}],"ebullient":[{"w":"ebullient","t":"a. 沸腾的, 热情的, 热情洋溢的","p":"i'bʌljәnt","d":"s. joyously unrestrained","c":1,"f":20110}],"ebulliently":[{"w":"ebulliently","t":"adv. ebullient的变形","d":"r in an ebullient manner"}],"ebulliometer":[{"w":"ebulliometer","t":"n. 沸点测定器, 酒精测量器","p":"i,bʌli'ɔmitә"}],"ebulliometry":[{"w":"ebulliometry","t":"沸点升高测定法","p":"i,bʌli'ɔmitri"}],"ebullioscope":[{"w":"ebullioscope","t":"n. 沸点测定器, 酒精测量器","p":"'ibʌliәskәup","d":"n. An instrument for observing the boiling point of\n   liquids, especially for determining the alcoholic strength of a mixture\n   by the temperature at which it boils."}],"ebullioscopic":[{"w":"ebullioscopic","t":"a. 沸点测定器的, 酒精测量器的","p":"i,bʌliә'skɔpik"}],"ebullioscopic constant":[{"w":"ebullioscopic constant","t":"[化] 沸点升高常数"}],"ebullioscopic equation":[{"w":"ebullioscopic equation","t":"[化] 沸点升高公式"}],"ebullioscopic solvent":[{"w":"ebullioscopic solvent","t":"[化] 沸点升高溶剂"}],"ebullioscopy":[{"w":"ebullioscopy","t":"n. 沸点升高测定法","p":"i,bʌli'ɔskәpi"}],"ebullism":[{"w":"ebullism","t":"n. [医](由于气压突然减低而出现的)体液沸腾","p":"'ebәlizm"}],"ebullition":[{"w":"ebullition","t":"n. 沸腾, (感情的)迸发\n[医] 沸, 沸腾","p":".ebә'liʃәn","d":"n an unrestrained expression of emotion"}],"ebur":[{"w":"ebur","t":"象牙","p":"'ebә"}],"ebur dentis":[{"w":"ebur dentis","t":"[医] 牙质, 牙本质"}],"eburnamonine":[{"w":"eburnamonine","t":"[化] 象牙酮宁"}],"eburnated":[{"w":"eburnated","t":"a. 似象牙般坚硬结实的","p":"'ebә:neitid"}],"eburnation":[{"w":"eburnation","t":"n. [医]骨质象牙化","p":",ibә'neiʃәn, ,i:bә'-","d":"n a change that occurs in degenerative joint disease in which bone is converted into a dense smooth substance resembling ivory"}],"eburnean":[{"w":"eburnean","t":"a. 象牙的, 似象牙的","p":"i'b\\\\\\\\:niәn","d":"a. Made of or relating to ivory."}],"eburneous":[{"w":"eburneous","t":"[医] 象牙样的"}],"eburnitis":[{"w":"eburnitis","t":"牙釉质密固","p":",i:bә'naitis"}],"eburophyton austinae":[{"w":"Eburophyton austinae","t":"[网络] 欧洲奥地利"}],"ebury":[{"w":"Ebury","t":"n. (Ebury)人名；(英)伊伯里","f":37957}],"ebv":[{"w":"EBV","t":"abbr. 电子制动力分配装置；乙脑疫苗","d":"n. the herpes virus that causes infectious mononucleosis; associated with specific cancers in Africa and China"}],"eby":[{"w":"eby","t":"[人名] 伊比"}]}