{"uv":[{"w":"uv","t":"abbr. 紫外的（ultraviolet）","d":"n radiation lying in the ultraviolet range; wave lengths shorter than light but longer than X rays","f":17186}],"uv spectrum":[{"w":"UV spectrum","t":"[化] 紫外光谱"}],"uv stabilizer":[{"w":"uv stabilizer","t":"[机] 紫外线稳定剂紫外线稳定剂"}],"uv-531":[{"w":"UV-531","t":"[化] 2-羟基-4-正辛氧基二苯甲酮"}],"uv-9":[{"w":"UV-9","t":"[化] 2-羟基-4-甲氧基二苯甲酮"}],"uv-b":[{"w":"uv-b","t":"[医][=ultraviolet-B radiation]紫外线B辐射"}],"uv-c":[{"w":"uv-c","t":"[医][=ultraviolet-C radiation]紫外线C辐射"}],"uv-induced":[{"w":"uv-induced","t":"[医]紫外线引起的"}],"uv-light":[{"w":"uv-light","t":"紫外光"}],"uv-p":[{"w":"UV-P","t":"[化] 2-苯并三唑; 2-2-羟基-5-甲基苯基苯并三唑"}],"uv-reflectance spectrometry":[{"w":"UV-reflectance spectrometry","t":"[化] 紫外反射光谱法"}],"uv-screen":[{"w":"UV-screen","t":"[化] 光屏蔽剂"}],"uva":[{"w":"uva","t":"[医] 葡萄干","d":"n. A small pulpy or juicy fruit containing several seeds and\n   having a thin skin, as a grape.","f":42514}],"uva ursi":[{"w":"uva ursi","t":"[医] 熊果"}],"uvaeformis":[{"w":"uvaeformis","t":"[医] 脉络膜中层"}],"uval":[{"w":"uval","t":"磺异苯酮"}],"uvala":[{"w":"uvala","t":"(=ouvala) 干[喀斯特]宽谷","p":"'u:vәlә"}],"uvalde":[{"w":"uvalde","t":"[地名] [美国] 尤瓦尔迪"}],"uvanite":[{"w":"uvanite","t":"钒铀矿","p":"'ju:vә,nait"}],"uvaol":[{"w":"uvaol","t":"熊果醇"}],"uvarov":[{"w":"uvarov","t":"[人名] 尤瓦罗夫"}],"uvarovite":[{"w":"uvarovite","t":"n. [矿]钙铬榴石","p":"u:'vɑ:rә,vait, ju'-"}],"uvaser":[{"w":"uvaser","t":"远紫外激光器","p":"ju:'veisә"}],"uvauum":[{"w":"uvauum","t":"n. 真空"}],"uvb":[{"w":"uvb","t":"[医][=ultraviolet light,midrange sunbeam spectrum]紫外线B光谱, 中波紫外线光谱","p":"ˌju: vi: ˈbi:","f":44502}],"uvc":[{"w":"UVC","t":"abbr. 万能接头（Universal Contact）"}],"uvea":[{"w":"uvea","t":"n. [解]眼色素层,葡萄膜","p":"'ju:viә","d":"n the part of the eye that contains the iris and ciliary body and choroid"}],"uveal":[{"w":"uveal","t":"[医] 眼色素层的","d":"a of or relating to the uvea of the eye"}],"uveal coat":[{"w":"uveal coat","t":"[医] 眼球中膜, 葡萄膜"}],"uveal framework":[{"w":"uveal framework","t":"[医] 虹膜梳状韧带"}],"uveal staphyloma":[{"w":"uveal staphyloma","t":"[医] 眼色素层葡萄肿"}],"uveal tract":[{"w":"uveal tract","t":"[医] 葡萄膜(包括虹膜、睫状体及脉络膜)"}],"uvedale":[{"w":"Uvedale","t":",Nicholas 尤夫德尔(即Udall,Nicholas)","p":"'ju:dəl,'ju:vdeil"}],"uveitic":[{"w":"uveitic","t":"[医] 眼色素层炎的"}],"uveitis":[{"w":"uveitis","t":"n. [医]眼色素层炎,葡萄膜炎","p":",ju:vi'aitis","d":"n inflammation of the uvea of the eye"}],"uveomeningitis":[{"w":"uveomeningitis","t":"眼色素膜脑膜炎"}],"uveoparotid":[{"w":"uveoparotid","t":"[医] 眼色素层腮腺的"}],"uveoparotid fever":[{"w":"uveoparotid fever","t":"[医] 眼色素层腮腺炎, 黑福特氏病"}],"uveoparotid tuberculosis":[{"w":"uveoparotid tuberculosis","t":"[医] 眼色素层腮腺炎"}],"uveoparotitic polyneuritis":[{"w":"uveoparotitic polyneuritis","t":"[医] 眼色素层腮腺炎性神经炎, 眼色素层腮腺炎"}],"uveoparotitis":[{"w":"uveoparotitis","t":"眼色素层腮腺炎","p":",juviәu,pærә'taits"}],"uveoplasty":[{"w":"uveoplasty","t":"眼色素层成形术","p":"'ju:viә,plæsti"}],"uveoscleral pathway":[{"w":"uveoscleral pathway","t":"[网络] 葡萄膜巩膜房水流出"}],"uveoscleritis":[{"w":"uveoscleritis","t":"眼色素层巩膜炎","p":",ju:viәu,skliә'raitis"}],"uveous":[{"w":"uveous","t":"[医]葡萄串状的","p":"'ʌvɪəs","d":"a. Resembling a grape."}],"uvf":[{"w":"UVF","t":"abbr. 紫外荧光（Ultraviolet Fluorescence）；（爱尔兰）阿尔斯特志愿者武装（Ulster Volunteer Force）"}],"uvic acid":[{"w":"uvic acid","t":"[化] 乌韦酸; 2,5-二甲基-3-呋喃羧酸"}],"uvicon":[{"w":"uvicon","t":"紫外二次电子导电管","p":"'ju:vi,kɔn"}],"uviform":[{"w":"uviform","t":"[医] 葡萄形的"}],"uvinic acid":[{"w":"uvinic acid","t":"[化] 乌韦酸"}],"uviofast":[{"w":"uviofast","t":"[医] 抗紫外线的"}],"uviol":[{"w":"uviol","t":"[医] 透紫外线玻璃"}],"uviol glass":[{"w":"uviol glass","t":"[化] 透紫外线玻璃"}],"uviol lamp":[{"w":"uviol lamp","t":"[医] 透紫[外线]玻璃灯"}],"uviol milk":[{"w":"uviol milk","t":"[医] 紫外线消毒乳"}],"uviolize":[{"w":"uviolize","t":"[医] 紫外线照射"}],"uviometer":[{"w":"uviometer","t":"[医] 紫外线测量计"}],"uvioresistant":[{"w":"uvioresistant","t":"[医] 抗紫外线的"}],"uviosensitive":[{"w":"uviosensitive","t":"[医] 紫外线敏感的"}],"uvira":[{"w":"uvira","t":"[地名] [刚果民主共和国] 乌维拉"}],"uvite":[{"w":"uvite","t":"钙镁电气石"}],"uvitic acid":[{"w":"uvitic acid","t":"[化] 乌韦特酸\n[医] 5-甲基苯间二甲酸"}],"uvitinic acid":[{"w":"uvitinic acid","t":"[化] 乌韦特酸"}],"uvitonic acid":[{"w":"uvitonic acid","t":"[化] 乌韦酮酸; 6-甲基-2,4-吡啶二甲酸"}],"uvm":[{"w":"uvm","t":"[医][=ultraviolet meter]紫外线计"}],"uvr":[{"w":"uvr","t":"abbr. ultraviolet radiation 紫外辐射; UV resistance determinant 紫外线耐力决定簇","p":"'ʌvr"}],"uvsc":[{"w":"uvsc","t":"abbr. ultraviolet solar constant 紫外线太阳常数","p":"'ʌvsk"}],"uvula":[{"w":"uvula","t":"n. 悬雍垂, 小舌\n[医] 悬雍垂","p":"'ju:vjulә","d":"n. a small pendant fleshy lobe at the back of the soft palate","f":39749}],"uvula cerebelli":[{"w":"uvula cerebelli","t":"[医] 小脑悬雍垂, 蚓垂"}],"uvula fissa":[{"w":"uvula fissa","t":"[医] 悬雍垂裂"}],"uvula forceps":[{"w":"uvula forceps","t":"[医] 悬壅垂钳"}],"uvula palatina":[{"w":"uvula palatina","t":"[医] 悬雍垂"}],"uvula vermis":[{"w":"uvula vermis","t":"[医] 小脑悬雍垂, 蚓垂"}],"uvula vesicae":[{"w":"uvula vesicae","t":"[医] 膀胱悬雍垂"}],"uvulae":[{"w":"uvulae","t":"uvula的复数形","p":"ˊjuːvjuliː","d":"n. a small pendant fleshy lobe at the back of the soft palate"}],"uvulaptosis":[{"w":"uvulaptosis","t":"[医] 悬雍垂下垂"}],"uvular":[{"w":"uvular","t":"a. 悬壅垂的, 小舌的\n[医] 悬雍垂的","p":"'ju:vjulә","d":"a. of or relating to or associated with the uvula"}],"uvular ptosis":[{"w":"uvular ptosis","t":"[医] 悬雍垂下垂"}],"uvularia":[{"w":"Uvularia","t":"[网络] 腭花属；剧烈变化可引起颚花属；垂铃儿属"}],"uvularia grandiflora":[{"w":"Uvularia grandiflora","t":"[网络] 大花铃铛花；大花宝铎花"}],"uvulariaceae":[{"w":"Uvulariaceae","t":"[网络] 悬阶草科"}],"uvularis":[{"w":"uvularis","t":"[医] 悬雍垂肌"}],"uvulatome":[{"w":"uvulatome","t":"[医] 悬雍垂刀","d":"n. An instrument for removing the uvula."}],"uvulatomy":[{"w":"uvulatomy","t":"n. [医]悬雍垂切开术,悬雍垂(部分)切除术","p":",ju:vjj'lætәmi","d":"n. The operation of removing the uvula."}],"uvulectomy":[{"w":"uvulectomy","t":"[医] 悬雍垂切除术"}],"uvulitis":[{"w":"uvulitis","t":"n. [医]悬雍垂炎","p":",ju:vjj'laitis","d":"n inflammation of the uvula"}],"uvulopalatopharyngoplasty":[{"w":"uvulopalatopharyngoplasty","t":"[医]悬雍垂-腭-咽成形术","p":"ju:vjʊləʊpælætəfeə'rɪŋɡɒp"}],"uvuloptosis":[{"w":"uvuloptosis","t":"[医] 悬雍垂下垂"}],"uvulorome":[{"w":"uvulorome","t":"[医] 悬雍垂刀"}],"uvulotome":[{"w":"uvulotome","t":"悬雍垂刀; 悬雍垂切断器"}],"uvulotomy":[{"w":"uvulotomy","t":"n. [医]悬雍垂切开术,悬雍垂(部分)切除术","p":",ju:vjj'lɔtәmi"}]}